cwpythonwrapper
cwpythonwrapper/models
