Metadata-Version: 1.0
Name: cwpythonwrapper
Version: 1.0.2
Summary: Python wrapper for Code Wars
Home-page: https://bitbucket.org/Arvraepe-jstack/codewars
Author: Michiel Dockx
Author-email: michieldx@gmail.com
License: UNKNOWN
Platform: UNKNOWN
